betterdxcam/__init__.py
betterdxcam/betterdxcam.py
betterdxcam/_libs/__init__.py
betterdxcam/_libs/d3d11.py
betterdxcam/_libs/dxgi.py
betterdxcam/_libs/user32.py
betterdxcam/core/__init__.py
betterdxcam/core/device.py
betterdxcam/core/duplicator.py
betterdxcam/core/output.py
betterdxcam/core/stagesurf.py
betterdxcam/processor/__init__.py
betterdxcam/processor/base.py
betterdxcam/processor/numpy_processor.py
betterdxcam/util/__init__.py
betterdxcam/util/io.py
betterdxcam/util/timer.py
betterDXcam-0.0.9.dist-info/LICENSE
betterDXcam-0.0.9.dist-info/METADATA
betterDXcam-0.0.9.dist-info/WHEEL
betterDXcam-0.0.9.dist-info/top_level.txt
betterDXcam-0.0.9.dist-info/RECORD
