Metadata-Version: 2.1
Name: betterDXcam
Version: 0.0.9
Summary: A Python high-performance screenshot library for Windows use Desktop Duplication API
Home-page: https://github.com/E1Bos/betterDXcam
Author: E1Bos
License: MIT
Project-URL: Source, https://github.com/E1Bos/betterdxcam
Project-URL: Tracker, https://github.com/E1Bos/betterdxcam/issues
Keywords: screen,screenshot,screencapture,screengrab,windows
Classifier: Development Status :: 2 - Pre-Alpha
Classifier: Intended Audience :: Developers
Classifier: Programming Language :: Python :: 3
Classifier: Programming Language :: Python :: 3 :: Only
Classifier: License :: OSI Approved :: MIT License
Classifier: Operating System :: Microsoft :: Windows
Classifier: Operating System :: Microsoft :: Windows :: Windows 10
Classifier: Operating System :: Microsoft :: Windows :: Windows 11
Classifier: Topic :: Multimedia :: Graphics
Classifier: Topic :: Multimedia :: Graphics :: Capture
Classifier: Topic :: Multimedia :: Graphics :: Capture :: Screen Capture
Requires-Python: >=3.7
License-File: LICENSE
Requires-Dist: numpy
Requires-Dist: comtypes
Provides-Extra: cv2
Requires-Dist: opencv-python ; extra == 'cv2'
